simple_pca/__init__.py
simple_pca/__main__.py
simple_pca-0.2.4.dist-info/LICENSE.txt
simple_pca-0.2.4.dist-info/METADATA
simple_pca-0.2.4.dist-info/WHEEL
simple_pca-0.2.4.dist-info/top_level.txt
simple_pca-0.2.4.dist-info/RECORD
