Metadata-Version: 2.1
Name: simple_pca
Version: 0.2.4
Summary: simple pca
Author-email: Johannes <johannes-programming@mailfence.com>
License: The MIT License (MIT)
Project-URL: Documentation, https://pypi.org/project/simple_pca
Project-URL: Download, https://pypi.org/project/simple-pca/#files
Project-URL: Source, https://github.com/johannes-programming/simple_pca
Classifier: License :: OSI Approved :: MIT License
Classifier: Programming Language :: Python
Classifier: Programming Language :: Python :: 3
Classifier: Programming Language :: Python :: 3 :: Only
Requires-Python: >=3.11
License-File: LICENSE.txt
Requires-Dist: click >=8.1.7
Requires-Dist: fileunity >=1.0.3
Requires-Dist: getoptify >=1.0.1
Requires-Dist: numpy >=1.26.1
Requires-Dist: pandas >=1.5.3
